<annotation>
	<folder>百度-美军舰船</folder>
	<filename>56-1.jpeg</filename>
	<path>D:\作业\图片\百度-美军舰船\56-1.jpeg</path>
	<source>
		<database>Unknown</database>
	</source>
	<size>
		<width>2000</width>
		<height>1312</height>
		<depth>3</depth>
	</size>
	<segmented>0</segmented>
	<object>
		<name>warship</name>
		<pose>Unspecified</pose>
		<truncated>0</truncated>
		<difficult>0</difficult>
		<bndbox>
			<xmin>201</xmin>
			<ymin>385</ymin>
			<xmax>1955</xmax>
			<ymax>1107</ymax>
		</bndbox>
	</object>
	<object>
		<name>56</name>
		<pose>Unspecified</pose>
		<truncated>0</truncated>
		<difficult>0</difficult>
		<bndbox>
			<xmin>379</xmin>
			<ymin>909</ymin>
			<xmax>511</xmax>
			<ymax>997</ymax>
		</bndbox>
	</object>
</annotation>
